nshtrainer/.nshconfig.generated.json
nshtrainer/__init__.py
nshtrainer/_callback.py
nshtrainer/_checkpoint/metadata.py
nshtrainer/_checkpoint/saver.py
nshtrainer/_experimental/__init__.py
nshtrainer/_hf_hub.py
nshtrainer/callbacks/__init__.py
nshtrainer/callbacks/actsave.py
nshtrainer/callbacks/base.py
nshtrainer/callbacks/checkpoint/__init__.py
nshtrainer/callbacks/checkpoint/_base.py
nshtrainer/callbacks/checkpoint/best_checkpoint.py
nshtrainer/callbacks/checkpoint/last_checkpoint.py
nshtrainer/callbacks/checkpoint/on_exception_checkpoint.py
nshtrainer/callbacks/debug_flag.py
nshtrainer/callbacks/directory_setup.py
nshtrainer/callbacks/distributed_prediction_writer.py
nshtrainer/callbacks/early_stopping.py
nshtrainer/callbacks/ema.py
nshtrainer/callbacks/finite_checks.py
nshtrainer/callbacks/gradient_skipping.py
nshtrainer/callbacks/interval.py
nshtrainer/callbacks/log_epoch.py
nshtrainer/callbacks/lr_monitor.py
nshtrainer/callbacks/metric_validation.py
nshtrainer/callbacks/norm_logging.py
nshtrainer/callbacks/print_table.py
nshtrainer/callbacks/rlp_sanity_checks.py
nshtrainer/callbacks/shared_parameters.py
nshtrainer/callbacks/timer.py
nshtrainer/callbacks/wandb_upload_code.py
nshtrainer/callbacks/wandb_watch.py
nshtrainer/configs/.gitattributes
nshtrainer/configs/__init__.py
nshtrainer/configs/_checkpoint/__init__.py
nshtrainer/configs/_checkpoint/metadata/__init__.py
nshtrainer/configs/_hf_hub/__init__.py
nshtrainer/configs/callbacks/__init__.py
nshtrainer/configs/callbacks/actsave/__init__.py
nshtrainer/configs/callbacks/base/__init__.py
nshtrainer/configs/callbacks/checkpoint/__init__.py
nshtrainer/configs/callbacks/checkpoint/_base/__init__.py
nshtrainer/configs/callbacks/checkpoint/best_checkpoint/__init__.py
nshtrainer/configs/callbacks/checkpoint/last_checkpoint/__init__.py
nshtrainer/configs/callbacks/checkpoint/on_exception_checkpoint/__init__.py
nshtrainer/configs/callbacks/debug_flag/__init__.py
nshtrainer-1.5.1.dist-info/METADATA
nshtrainer-1.5.1.dist-info/WHEEL
nshtrainer-1.5.1.dist-info/RECORD
