Metadata-Version: 2.3
Name: nshtrainer
Version: 1.5.1
Summary: 
Author: Nima Shoghi
Author-email: nimashoghi@gmail.com
Requires-Python: >=3.10,<4.0
Classifier: Programming Language :: Python :: 3
Classifier: Programming Language :: Python :: 3.10
Classifier: Programming Language :: Python :: 3.11
Classifier: Programming Language :: Python :: 3.12
Classifier: Programming Language :: Python :: 3.13
Provides-Extra: extra
Requires-Dist: GitPython ; extra == "extra"
Requires-Dist: huggingface-hub ; extra == "extra"
Requires-Dist: lightning
Requires-Dist: nshconfig (>=0.43)
Requires-Dist: nshrunner ; extra == "extra"
Requires-Dist: nshutils ; extra == "extra"
Requires-Dist: numpy
Requires-Dist: packaging
Requires-Dist: psutil
Requires-Dist: tensorboard ; extra == "extra"
Requires-Dist: torch
Requires-Dist: torchmetrics
Requires-Dist: typing-extensions
Requires-Dist: wandb ; extra == "extra"
Requires-Dist: wrapt ; extra == "extra"
